README.md
setup.py
tseq2seq/__init__.py
tseq2seq/seq2seq.py
tseq2seq/ts2s.py
tseq2seq.egg-info/PKG-INFO
tseq2seq.egg-info/SOURCES.txt
tseq2seq.egg-info/dependency_links.txt
tseq2seq.egg-info/requires.txt
tseq2seq.egg-info/top_level.txt