Metadata-Version: 1.0
Name: tseq2seq
Version: 0.1.0.11572551129.4685054
Summary: tseq2seq
Home-page: https://github.com/napoler/tseq2seq
Author: Terry Chan
Author-email: napoler2008@gmail.com
License: UNKNOWN
Platform: UNKNOWN
